[
  {
    "user": 8539834024,
    "movie": "Maya - Tamil",
    "time": "2026-04-29T12:01:41.255Z",
    "status": "Fulfilled"
  },
  {
    "user": 8313837482,
    "movie": "the boy who harness the rain",
    "time": "2026-04-30T07:17:02.605Z",
    "status": "Fulfilled"
  },
  {
    "user": 7014767213,
    "movie": "movie",
    "time": "2026-04-30T07:41:08.264Z",
    "status": "Fulfilled"
  },
  {
    "user": 5948789897,
    "movie": "kd the devil",
    "time": "2026-04-30T07:59:53.626Z",
    "status": "Fulfilled"
  },
  {
    "user": 5948789897,
    "movie": "KD – The Devil",
    "time": "2026-04-30T08:02:33.877Z",
    "status": "Fulfilled"
  },
  {
    "user": 5948789897,
    "movie": "behrupiyo",
    "time": "2026-04-30T12:18:32.536Z",
    "status": "Fulfilled"
  },
  {
    "user": 1928720831,
    "movie": "website",
    "time": "2026-04-30T16:31:07.157Z",
    "status": "Fulfilled"
  },
  {
    "user": 5948789897,
    "movie": "KD – The Devil",
    "time": "2026-04-30T17:05:16.105Z",
    "status": "Fulfilled"
  },
  {
    "user": 1057532066,
    "movie": "waktu maghrib",
    "time": "2026-04-30T18:04:26.175Z",
    "status": "Fulfilled"
  },
  {
    "user": 1057532066,
    "movie": "The Wailing of the Maghrib",
    "time": "2026-04-30T18:07:35.738Z",
    "status": "Fulfilled"
  },
  {
    "user": 7750709359,
    "movie": "bhoot bangla at 1080 hp",
    "time": "2026-04-30T18:18:08.964Z",
    "status": "Fulfilled"
  },
  {
    "user": 5951923988,
    "movie": "hrllo",
    "time": "2026-04-30T19:50:52.789Z",
    "status": "Fulfilled"
  },
  {
    "user": 5951923988,
    "movie": "iron man",
    "time": "2026-04-30T19:54:23.135Z",
    "status": "Fulfilled"
  },
  {
    "user": 5951923988,
    "movie": "robot",
    "time": "2026-04-30T20:16:08.663Z",
    "status": "Fulfilled"
  },
  {
    "user": 5951923988,
    "movie": "gadar",
    "time": "2026-04-30T20:18:02.052Z",
    "status": "Fulfilled"
  },
  {
    "user": 5951923988,
    "movie": "Ek Din Achanak (1989)",
    "language": "Hindi",
    "time": "2026-05-01T01:42:32.188Z",
    "status": "Fulfilled"
  },
  {
    "user": 2138972360,
    "movie": "Bhoot Bungla (1965)",
    "language": "Hindi",
    "time": "2026-05-01T06:13:01.102Z",
    "status": "Fulfilled"
  },
  {
    "user": 5951923988,
    "movie": "dead",
    "time": "2026-05-01T07:31:02.353Z",
    "status": "Fulfilled"
  },
  {
    "user": 5951923988,
    "movie": "The Hurricane Heist (2018)",
    "language": "English",
    "time": "2026-05-01T07:32:02.520Z",
    "status": "Fulfilled"
  },
  {
    "user": 5951923988,
    "movie": "jadu",
    "time": "2026-05-01T07:32:27.861Z",
    "status": "Fulfilled"
  },
  {
    "user": 5951923988,
    "movie": "not",
    "time": "2026-05-01T07:33:01.935Z",
    "status": "Fulfilled"
  },
  {
    "user": 2047443453,
    "movie": "bhoot bangla",
    "time": "2026-05-01T07:42:12.344Z",
    "status": "Fulfilled"
  },
  {
    "user": 1730810185,
    "movie": "Patriot (2026)",
    "language": "Malayalam",
    "time": "2026-05-01T08:15:10.315Z",
    "status": "Pending"
  },
  {
    "user": 1057532066,
    "movie": "Kambakkht Ishq (2009)",
    "language": "Hindi",
    "time": "2026-05-01T08:49:18.049Z",
    "status": "Fulfilled"
  },
  {
    "user": 5394607303,
    "movie": "movie",
    "time": "2026-05-01T09:14:56.153Z",
    "status": "Pending"
  },
  {
    "user": 8346557188,
    "movie": "Raja Shivaji (2026)",
    "language": "Marathi",
    "time": "2026-05-01T09:17:40.112Z",
    "status": "Pending"
  },
  {
    "user": 5991594350,
    "movie": "bhoot bangla",
    "time": "2026-05-01T09:20:03.389Z",
    "status": "Pending"
  },
  {
    "user": 1057532066,
    "movie": "Snack Shack (2024)",
    "language": "English",
    "time": "2026-05-01T12:45:18.444Z",
    "status": "Fulfilled"
  },
  {
    "user": 8539834024,
    "movie": "bhoot bangla",
    "time": "2026-05-01T15:24:36.161Z",
    "status": "Pending"
  },
  {
    "user": 5951923988,
    "movie": "Sex Trip (2026)",
    "language": "TL",
    "time": "2026-05-01T16:03:22.875Z",
    "status": "Pending"
  },
  {
    "user": 5951923988,
    "movie": "Raja Shivaji (2026)",
    "language": "Marathi",
    "time": "2026-05-01T16:05:47.644Z",
    "status": "Pending"
  }
]